{
    "$schema": "https://json-schema.org/draft/2020-12/schema",
    "$comment": "https://openid.net/specs/openid-4-verifiable-credential-issuance-1_0.html",
    "type": "object",
    "properties": {
        "credential_issuer": {
            "type": "string"
        },
        "authorization_servers": {
            "type": "array",
            "items": {
                "type": "string"
            }
        },
        "credential_endpoint": {
            "type": "string",
            "format": "uri"
        },
        "nonce_endpoint": {
            "type": "string",
            "format": "uri"
        },
        "deferred_credential_endpoint": {
            "type": "string",
            "format": "uri"
        },
        "notification_endpoint": {
            "type": "string",
            "format": "uri"
        },
        "credential_response_encryption": {
            "type": "object",
            "properties": {
                "alg_values_supported": {
                    "type": "array",
                    "items": {
                        "type": "string"
                    }
                },
                "enc_values_supported": {
                    "type": "array",
                    "items": {
                        "type": "string"
                    }
                },
                "encryption_required": {
                    "type": "boolean"
                }
            },
            "required": [
                "alg_values_supported",
                "enc_values_supported",
                "encryption_required"
            ]
        },
        "batch_credential_issuance": {
            "type": "object",
            "properties": {
                "batch_size": {
                    "type": "integer",
                    "minimum": 1
                }
            },
            "required": [
                "batch_size"
            ]
        },
        "signed_metadata": {
            "type": "string"
        },
        "display": {
            "type": "array",
            "items": {
                "type": "object",
                "properties": {
                    "name": {
                        "type": "string"
                    },
                    "locale": {
                        "type": "string"
                    },
                    "logo": {
                        "type": "object",
                        "properties": {
                            "uri": {
                                "type": "string",
                                "format": "uri"
                            },
                            "alt_text": {
                                "type": "string"
                            }
                        },
                        "required": [
                            "uri"
                        ]
                    }
                }
            }
        },
        "credential_configurations_supported": {
            "type": "object",
            "additionalProperties": {
                "allOf": [
                    {
                        "type": "object",
                        "properties": {
                            "format": {
                                "type": "string"
                            },
                            "scope": {
                                "type": "string"
                            },
                            "cryptographic_binding_methods_supported": {
                                "type": "array",
                                "items": {
                                    "type": "string"
                                }
                            },
                            "proof_types_supported": {
                                "type": "object",
                                "additionalProperties": {
                                    "type": "object",
                                    "properties": {
                                        "proof_signing_alg_values_supported": {
                                            "type": "array",
                                            "items": {
                                                "type": "string"
                                            }
                                        }
                                    },
                                    "required": [
                                        "proof_signing_alg_values_supported"
                                    ]
                                }
                            },
                            "display": {
                                "type": "array",
                                "items": {
                                    "type": "object",
                                    "properties": {
                                        "name": {
                                            "type": "string"
                                        },
                                        "locale": {
                                            "type": "string"
                                        },
                                        "logo": {
                                            "type": "object",
                                            "properties": {
                                                "uri": {
                                                    "type": "string",
                                                    "format": "uri"
                                                },
                                                "alt_text": {
                                                    "type": "string"
                                                }
                                            },
                                            "required": [
                                                "uri"
                                            ]
                                        },
                                        "description": {
                                            "type": "string"
                                        },
                                        "background_color": {
                                            "type": "string"
                                        },
                                        "background_image": {
                                            "type": "object",
                                            "properties": {
                                                "uri": {
                                                    "type": "string",
                                                    "format": "uri"
                                                }
                                            },
                                            "required": [
                                                "uri"
                                            ]
                                        },
                                        "text_color": {
                                            "type": "string"
                                        }
                                    }
                                }
                            }
                        },
                        "required": [
                            "format"
                        ]
                    },
                    {
                        "if": {
                            "properties": {
                                "format": {
                                    "const": "dc+sd-jwt"
                                }
                            }
                        },
                        "then": {
                            "properties": {
                                "vct": {
                                    "type": "string",
                                    "description": "String designating the type of a Credential."
                                },
                                "credential_signing_alg_values_supported": {
                                    "type": "array",
                                    "items": {
                                        "type": "string"
                                    }
                                },
                                "claims": {
                                    "type": "array",
                                    "description": "An array of claims description objects.",
                                    "items": {
                                        "type": "object",
                                        "properties": {
                                            "path": {
                                                "type": "array",
                                                "description": "A non-empty array representing a claims path pointer.",
                                                "items": {
                                                    "type": "string"
                                                },
                                                "minItems": 1
                                            },
                                            "mandatory": {
                                                "type": "boolean",
                                                "default": false
                                            },
                                            "display": {
                                                "type": "array",
                                                "items": {
                                                    "type": "object",
                                                    "properties": {
                                                        "name": {
                                                            "type": "string"
                                                        },
                                                        "locale": {
                                                            "type": "string",
                                                            "description": "BCP47 language tag."
                                                        }
                                                    }
                                                }
                                            }
                                        },
                                        "required": [
                                            "path"
                                        ]
                                    }
                                }
                            },
                            "required": [
                                "vct"
                            ]
                        }
                    },
                    {
                        "if": {
                            "properties": {
                                "format": { "const": "mso_mdoc" }
                            }
                        },
                        "then": {
                            "properties": {
                                "doctype": {
                                    "type": "string",
                                    "description": "String identifying the Credential type (mdoc doctype)."
                                },
                                "credential_signing_alg_values_supported": {
                                    "type": "array",
                                    "items": {
                                        "oneOf": [
                                            { "type": "integer" }
                                        ]
                                    }
                                }
                            },
                            "required": ["doctype"]
                        }
                    }
                ]
            }
        }
    },
    "required": [
        "credential_issuer",
        "credential_endpoint",
        "credential_configurations_supported"
    ]
}
